DeToX/Base.py
DeToX/Calibration.py
DeToX/Coords.py
DeToX/ETSettings.py
DeToX/Utils.py
DeToX/__init__.py
dvst_detox-0.1.0b1.dist-info/METADATA
dvst_detox-0.1.0b1.dist-info/WHEEL
dvst_detox-0.1.0b1.dist-info/top_level.txt
dvst_detox-0.1.0b1.dist-info/RECORD
