Metadata-Version: 2.4
Name: dvst-detox
Version: 0.1.0b1
Summary: Lightweight Python wrapper around tobii-researcher
Author-email: Tommaso Ghilardi <tommaso.ghilardi93@gmail.com>
Requires-Python: >=3.10
Requires-Dist: tobii-research
Requires-Dist: psychopy
